Neuron/__init__.py
Neuron/perceptron.py
Neuron_pypi_SivaNagendra_sn-0.0.3.dist-info/LICENSE
Neuron_pypi_SivaNagendra_sn-0.0.3.dist-info/METADATA
Neuron_pypi_SivaNagendra_sn-0.0.3.dist-info/WHEEL
Neuron_pypi_SivaNagendra_sn-0.0.3.dist-info/top_level.txt
Neuron_pypi_SivaNagendra_sn-0.0.3.dist-info/RECORD
