Metadata-Version: 2.1
Name: Neuron-pypi-SivaNagendra-sn
Version: 0.0.3
Summary: Yhis package implements perceptron
Home-page: https://github.com/SivaNagendra-sn/Neuron_pypi
Author: SivaNagendra-sn
Author-email: sivanagendra.paruchuri@gmail.com
License: UNKNOWN
Project-URL: Bug Tracker, https://github.com/SivaNagendra-sn/Neuron_pypi/issues
Platform: UNKNOWN
Classifier: Programming Language :: Python :: 3
Classifier: License :: OSI Approved :: MIT License
Classifier: Operating System :: OS Independent
Requires-Python: >=3.7
License-File: LICENSE
Requires-Dist: numpy
Requires-Dist: tqdm
